MANIFEST.in
README.md
setup.py
avtraj/__init__.py
avtraj/av_functions.py
avtraj/dye_definition.json
avtraj/elements.json
avtraj/sobol_lib.py
avtraj.egg-info/PKG-INFO
avtraj.egg-info/SOURCES.txt
avtraj.egg-info/dependency_links.txt
avtraj.egg-info/requires.txt
avtraj.egg-info/top_level.txt
doc/.log
doc/JSON Types and Parameters_TP1.docx
doc/api.rst
doc/avparameters.rst
doc/conf.py
doc/index.rst
doc/installation.rst
doc/make.bat
doc/tutorial.rst
doc/~$ON Types and Parameters_TP1.docx