Metadata-Version: 2.1
Name: avtraj
Version: 0.0.8
Summary: A library to calculate FRET observables for MD trajectories by accessible volume (AV) simulations.In the AV simulations the sterically allowed conformation space of the labels is approximated the conformational space of flexible attached ellipsoids.
Home-page: https://github.com/Fluorescence-Tools/avtraj
Author: Thomas-Otavio Peulen
Author-email: thomas.otavio.peulen@gmail.com
License: LGPLv2.1
Platform: UNKNOWN
Classifier: Programming Language :: Python
Classifier: Programming Language :: Python :: 2
Classifier: Programming Language :: Python :: 2.6
Classifier: Programming Language :: Python :: 2.7
Classifier: Programming Language :: Python :: 3
Classifier: Development Status :: 4 - Beta
Classifier: Environment :: Other Environment
Classifier: Intended Audience :: Science/Research
Classifier: License :: OSI Approved :: GNU Library or Lesser General Public License (LGPL)
Classifier: Operating System :: OS Independent
Classifier: Topic :: Software Development :: Libraries :: Python Modules
Classifier: Topic :: Scientific/Engineering
